fl_networking_tools/__init__.py
fl_networking_tools/binary_messaging.py
fl_networking_tools/image_viewer.py
fl_networking_tools/text_messaging.py
fl_networking_tools-0.0.6.dist-info/LICENSE.md
fl_networking_tools-0.0.6.dist-info/METADATA
fl_networking_tools-0.0.6.dist-info/WHEEL
fl_networking_tools-0.0.6.dist-info/top_level.txt
fl_networking_tools-0.0.6.dist-info/RECORD
